setup.py
DynamicPool/DynamicPool.py
DynamicPool/__init__.py
DynamicPool.egg-info/PKG-INFO
DynamicPool.egg-info/SOURCES.txt
DynamicPool.egg-info/dependency_links.txt
DynamicPool.egg-info/top_level.txt