Metadata-Version: 1.0
Name: DynamicPool
Version: 0.14
Summary: 动态任务阻塞线程/进程池
Home-page: https://github.com/Lzejie/DynamicPool
Author: L_zejie
Author-email: lzj_xuexi@163.com
License: MIT Licence
Keywords: Thread Pool,Dynamic Pool,Dynamic Thread Pool,Dynamic Process Pool
Platform: UNKNOWN
